binning_utils/__init__.py
binning_utils/power.py
binning_utils/power10.py
binning_utils/sphere.py
binning_utils/version.py
binning_utils_sebastian_achim_mueller-0.0.20.dist-info/licenses/LICENSE
binning_utils_sebastian_achim_mueller-0.0.20.dist-info/METADATA
binning_utils_sebastian_achim_mueller-0.0.20.dist-info/WHEEL
binning_utils_sebastian_achim_mueller-0.0.20.dist-info/top_level.txt
binning_utils_sebastian_achim_mueller-0.0.20.dist-info/RECORD
